README
dpaster
setup.py
dpaster.egg-info/PKG-INFO
dpaster.egg-info/SOURCES.txt
dpaster.egg-info/dependency_links.txt
dpaster.egg-info/requires.txt
dpaster.egg-info/top_level.txt
dpasterlib/__init__.py
dpasterlib/dpaster.py
dpasterlib/kdpaster.py