Metadata-Version: 1.0
Name: dpaster
Version: 0.2.0
Summary: dpaster is a quick & dirty client interface to to the http://dpaste.com/ pastebin.
Home-page: UNKNOWN
Author: UNKNOWN
Author-email: UNKNOWN
License: UNKNOWN
Platform: UNKNOWN
